Metadata-Version: 2.1
Name: scSIGRN
Version: 0.0.7
Summary: GRN inference
Home-page: https://github.com/lryup/SIGRN
Author: Rongyuan
Author-email: 2530506931@qq.com
Classifier: Programming Language :: Python :: 3
Classifier: License :: OSI Approved :: MIT License
Classifier: Operating System :: OS Independent
Requires-Python: >=3.7
License-File: LICENSE.txt
